openai_ui/__init__.py
openai_ui/__main__.py
openai_ui-0.0.1.dist-info/LICENSE
openai_ui-0.0.1.dist-info/METADATA
openai_ui-0.0.1.dist-info/WHEEL
openai_ui-0.0.1.dist-info/entry_points.txt
openai_ui-0.0.1.dist-info/top_level.txt
openai_ui-0.0.1.dist-info/zip-safe
openai_ui-0.0.1.dist-info/RECORD
